geci_referee/__init__.py
geci_referee/referee.py
geci_referee-0.2.0.dist-info/LICENSE
geci_referee-0.2.0.dist-info/WHEEL
geci_referee-0.2.0.dist-info/METADATA
geci_referee-0.2.0.dist-info/RECORD
