Metadata-Version: 2.1
Name: geci_referee
Version: 0.2.0
Summary: Common Task Framework Referee
Home-page: https://github.com/IslasGECI/referee_cat_recognition
Author: Ciencia de Datos • GECI
Author-email: ciencia.datos@islas.org.mx
Requires-Python: >=3.9
Classifier: License :: OSI Approved :: GNU General Public License v3 or later (GPLv3+)
